[{"userName":"a","email":"houtan@loagency.de","passWord1":"a","task":[{"taskTitle":"Diet","taskDate":"2022-05-27","isDone":0,"id":1},{"taskTitle":"asas","taskDate":"2022-06-03","isDone":0,"id":2},{"taskTitle":"asd","taskDate":"2022-05-31","isDone":0,"id":3},{"taskTitle":"","taskDate":"","isDone":0,"id":4},{"taskTitle":"aaa","taskDate":"2022-05-11","isDone":0,"id":5},{"taskTitle":"qqqqqqqqqqqqqqq","taskDate":"2022-06-01","isDone":0,"id":6},{"taskTitle":"ggggggggggggddddd","taskDate":"2022-05-28","isDone":0,"id":7}],"id":1}]